{
    "coord": {
        "lon": -0.07,
        "lat": 51.45
    },
    "weather": [
        {
            "id": 701,
            "main": "Mist",
            "description": "mist",
            "icon": "50n"
        },
        {
            "id": 741,
            "main": "Fog",
            "description": "fog",
            "icon": "50n"
        }
    ],
    "base": "stations",
    "main": {
        "temp": 13.87,
        "pressure": 1014,
        "humidity": 93,
        "temp_min": 13,
        "temp_max": 15
    },
    "visibility": 1100,
    "wind": {
        "speed": 1.5
    },
    "clouds": {
        "all": 90
    },
    "dt": 1539629400,
    "sys": {
        "type": 1,
        "id": 5091,
        "message": 0.0026,
        "country": "GB",
        "sunrise": 1539584717,
        "sunset": 1539623136
    },
    "id": 6690877,
    "name": "Brixton",
    "cod": 200
}